odoo8_addon_business_requirement-8.0.5.1.3-py2.7-nspkg.pth
odoo8_addon_business_requirement-8.0.5.1.3.dist-info/DESCRIPTION.rst
odoo8_addon_business_requirement-8.0.5.1.3.dist-info/METADATA
odoo8_addon_business_requirement-8.0.5.1.3.dist-info/RECORD
odoo8_addon_business_requirement-8.0.5.1.3.dist-info/WHEEL
odoo8_addon_business_requirement-8.0.5.1.3.dist-info/metadata.json
odoo8_addon_business_requirement-8.0.5.1.3.dist-info/namespace_packages.txt
odoo8_addon_business_requirement-8.0.5.1.3.dist-info/top_level.txt
odoo_addons/business_requirement/README.rst
odoo_addons/business_requirement/__init__.py
odoo_addons/business_requirement/__openerp__.py
odoo_addons/business_requirement/data/business_data.xml
odoo_addons/business_requirement/migrations/8.0.5.1.3/post-br-populate-responsible.py
odoo_addons/business_requirement/models/__init__.py
odoo_addons/business_requirement/models/business.py
odoo_addons/business_requirement/models/project.py
odoo_addons/business_requirement/security/ir.model.access.csv
odoo_addons/business_requirement/security/security.xml
odoo_addons/business_requirement/static/description/icon.png
odoo_addons/business_requirement/static/img/br_workflow.graphml
odoo_addons/business_requirement/static/img/bus_req.png
odoo_addons/business_requirement/static/img/bus_req_alias.png
odoo_addons/business_requirement/static/img/bus_req_approved.png
odoo_addons/business_requirement/static/img/bus_req_cancel.png
odoo_addons/business_requirement/static/img/bus_req_confirmed.png
odoo_addons/business_requirement/static/img/bus_req_cust_story.png
odoo_addons/business_requirement/static/img/bus_req_done.png
odoo_addons/business_requirement/static/img/bus_req_drop.png
odoo_addons/business_requirement/static/img/bus_req_module_diag.png
odoo_addons/business_requirement/static/img/bus_req_tags.png
odoo_addons/business_requirement/static/img/bus_req_tags2.png
odoo_addons/business_requirement/static/img/bus_req_tree.png
odoo_addons/business_requirement/static/img/bus_req_workflow.png
odoo_addons/business_requirement/static/img/module_diag.graphml
odoo_addons/business_requirement/tests/__init__.py
odoo_addons/business_requirement/tests/test_br.py
odoo_addons/business_requirement/tests/test_project.py
odoo_addons/business_requirement/views/business_view.xml
odoo_addons/business_requirement/views/project.xml
